fold/__init__.py
fold/integration.py
fold/model_selection/__init__.py
fold/model_selection/base.py
fold/model_selection/config.py
fold/model_selection/coverage.py
fold/model_selection/duration.py
fold/model_selection/models/__init__.py
fold/model_selection/models/calendar_split.py
fold/model_selection/models/expanding_n_split.py
fold/model_selection/models/expanding_split.py
fold/model_selection/models/function_split.py
fold/model_selection/models/grouper_split.py
fold/model_selection/models/interval_split.py
fold/model_selection/models/period_split.py
fold/model_selection/models/purged_kfold_cv.py
fold/model_selection/models/purged_kfold_split.py
fold/model_selection/models/purged_split.py
fold/model_selection/models/purged_walk_forward_cv.py
fold/model_selection/models/purged_walk_forward_split.py
fold/model_selection/models/random_n_split.py
fold/model_selection/models/rolling_n_split.py
fold/model_selection/models/rolling_optimize_split.py
fold/model_selection/models/rolling_split.py
fold/model_selection/models/single_split.py
fold/model_selection/models/sklearn_split.py
fold/model_selection/models/train_test_split.py
fold/model_selection/plots.py
fold/tools/__init__.py
fold/tools/base.py
fold/tools/periods.py
fold/tools/selectors.py
fold/tools/utils.py
fold/utils/__init__.py
fold/utils/checks.py
fold/utils/datetime.py
fold/utils/grouper.py
fold/utils/indexing.py
fold/utils/resampler.py
python_fold-0.1.2.dist-info/LICENSE
python_fold-0.1.2.dist-info/METADATA
python_fold-0.1.2.dist-info/WHEEL
python_fold-0.1.2.dist-info/RECORD
