Metadata-Version: 2.1
Name: python-fold
Version: 0.1.2
Summary: Time-series cross-validation on steroids. Multi-purpose. Fully compatible with scikit-learn.
Home-page: https://github.com/ActurialCapital/fold
License: BSD 3-Clause License
Author: ActurialCapital
Requires-Python: >=3.11,<4.0
Classifier: License :: Other/Proprietary License
Classifier: Programming Language :: Python :: 3
Classifier: Programming Language :: Python :: 3.11
Classifier: Programming Language :: Python :: 3.12
Requires-Dist: dateparser (>=1.2.0,<2.0.0)
Requires-Dist: numba (>=0.59.1,<0.60.0)
Requires-Dist: numpy (>=1.26.4,<2.0.0)
Requires-Dist: pandas (>=2.2.2,<3.0.0)
Requires-Dist: plotly (>=5.22.0,<6.0.0)
Requires-Dist: scikit-learn (>=1.4.2,<2.0.0)
Project-URL: Repository, https://github.com/ActurialCapital/fold
